{
    "id": 42584142,
    "name": "Bloodlust",
    "author": "knobbelboy",
    "creators": ["Endlevel", "Deadlox", "Antares", "CuLuC"],
    "verifier": "Skarro",
    "verification": "https://www.youtube.com/watch?v=cZfO579Yhjw",
    "percentToQualify": "100",
    "password": "789123",
    "records": [
        {
            "user": "BrightBird",
            "link": "https://www.youtube.com/watch?v=Uvrn_Gbangk",
            "percent": 100,
            "hz": 360
        },
        {
            "user": "Brandon Larkin",
            "link": "https://www.youtube.com/watch?v=4yEpF90XytQ",
            "percent": 100,
            "hz": 360
        },
        {
            "user": "Javei23",
            "link": "https://www.youtube.com/watch?v=G17J5-v_jZs",
            "percent": 100,
            "hz": 360
        }
    ]
}
