{
    "id": 76159410,
    "name": "Cosmic Cyclone",
    "author": "APTeam",
    "creators": ["FiryTheGoat", "KrazyGFX", "Riot", "Reunomi", "Avati", "Uriun", "GD Endy", "Shant", "Zimnior12", "Nickalopogas", "Zhander", "Tribar", "Lambda", "Realvet", "Cyclic", "Zuku", "CuLuC", "Sunix", "AppleCr", "Meox", "Zipixbox", "Requiem", "Heso"],
    "verifier": "attrixia",
    "verification": "https://www.youtube.com/watch?v=whLuRHsq7Z0",
    "percentToQualify": "100",
    "password": "Free to Copy",
    "records": [
    ]
}
